translator/__init__.py
translator/cli.py
translator/core.py
translator/keywords.py
translator/runtime.py
thai_python_translator-0.1.2.dist-info/METADATA
thai_python_translator-0.1.2.dist-info/WHEEL
thai_python_translator-0.1.2.dist-info/entry_points.txt
thai_python_translator-0.1.2.dist-info/licenses/LICENSE
thai_python_translator-0.1.2.dist-info/RECORD
