Metadata-Version: 2.3
Name: thai-python-translator
Version: 0.1.2
Summary: A tool to write Python code using Thai syntax
Project-URL: Homepage, https://github.com/yourusername/thai-python-translator
Project-URL: Repository, https://github.com/yourusername/thai-python-translator
Project-URL: Issues, https://github.com/yourusername/thai-python-translator/issues
Author-email: Tobias Andraschko <inquiries@ta-software-solutions.de>
License: MIT License
Keywords: education,language,python,thai,translator
Classifier: Development Status :: 4 - Beta
Classifier: Environment :: Console
Classifier: Intended Audience :: Developers
Classifier: Intended Audience :: Education
Classifier: License :: OSI Approved :: MIT License
Classifier: Programming Language :: Python :: 3
Classifier: Programming Language :: Python :: 3.6
Classifier: Programming Language :: Python :: 3.7
Classifier: Programming Language :: Python :: 3.8
Classifier: Programming Language :: Python :: 3.9
Classifier: Programming Language :: Python :: 3.10
Classifier: Programming Language :: Python :: 3.11
Classifier: Programming Language :: Python :: 3.12
Classifier: Topic :: Education
Classifier: Topic :: Software Development :: Libraries :: Python Modules
Requires-Python: >=3.6
